setup.py
hocr.egg-info/PKG-INFO
hocr.egg-info/SOURCES.txt
hocr.egg-info/dependency_links.txt
hocr.egg-info/entry_points.txt
hocr.egg-info/requires.txt
hocr.egg-info/top_level.txt
src/hocr/__init__.py
src/hocr/commands.py
src/hocr/meta.py
src/hocr/overlay.py
src/hocr/page.py
src/hocr/parser.py