Metadata-Version: 1.1
Name: hocr
Version: 0.2.6
Summary: HOCR manipulation and utility library; provides hocr2pdf binary.
Home-page: https://github.com/concordusapps/python-hocr
Author: Concordus Applications
Author-email: support@concordusapps.com
License: UNKNOWN
Platform: UNKNOWN
Classifier: Development Status :: 3 - Alpha
Classifier: Intended Audience :: Developers
Classifier: Intended Audience :: System Administrators
Classifier: License :: OSI Approved :: MIT License
Classifier: Operating System :: OS Independent
Classifier: Programming Language :: Python :: 3.3
